emailtracker/__init__.py
emailtracker/emailtracker.py
emailtracker-1.0.dist-info/LICENSE
emailtracker-1.0.dist-info/METADATA
emailtracker-1.0.dist-info/WHEEL
emailtracker-1.0.dist-info/entry_points.txt
emailtracker-1.0.dist-info/top_level.txt
emailtracker-1.0.dist-info/RECORD
