Metadata-Version: 2.1
Name: emailtracker
Version: 1.0
Summary: A graphical email tracking tool
Home-page: https://github.com/IMApurbo/emailtracker
Author: AKM Korishee Apurbo
Author-email: bandinvisible8@gmail.com
License: MIT
Classifier: License :: OSI Approved :: MIT License
Classifier: Programming Language :: Python :: 3
Classifier: Programming Language :: Python :: 3.6
Classifier: Programming Language :: Python :: 3.7
Classifier: Programming Language :: Python :: 3.8
Classifier: Programming Language :: Python :: 3.9
License-File: LICENSE
